django_staffio/__init__.py
django_staffio/auth_backend.py
flask_staffio/__init__.py
flask_staffio/client.py
flask_staffio/user.py
staffio-0.3.8.dist-info/DESCRIPTION.rst
staffio-0.3.8.dist-info/METADATA
staffio-0.3.8.dist-info/RECORD
staffio-0.3.8.dist-info/WHEEL
staffio-0.3.8.dist-info/metadata.json
staffio-0.3.8.dist-info/top_level.txt
