Metadata-Version: 2.0
Name: staffio
Version: 0.3.8
Summary: 
Requires-Dist: future
Provides-Extra: django
Requires-Dist: Django (>=1.6.0); extra == 'django'
Provides-Extra: flask
Requires-Dist: Flask; extra == 'flask'
Requires-Dist: Flask-OAuthlib (>=0.9.3); extra == 'flask'
Provides-Extra: sentry
Requires-Dist: sentry (>=8.0); extra == 'sentry'
Requires-Dist: oauth2; extra == 'sentry'
